casper7_plugin_meatball_day/__init__.py
casper7_plugin_meatball_day/db.py
casper7_plugin_meatball_day/run.py
casper7_plugin_meatball_day/settings.py
casper7_plugin_meatball_day/tables.py
casper7_plugin_meatball_day-0.4.2.dist-info/entry_points.txt
casper7_plugin_meatball_day-0.4.2.dist-info/WHEEL
casper7_plugin_meatball_day-0.4.2.dist-info/METADATA
casper7_plugin_meatball_day-0.4.2.dist-info/RECORD
