Metadata-Version: 2.1
Name: casper7-plugin-meatball-day
Version: 0.4.2
Summary: 
Author: backwardspy
Author-email: backwardspy@gmail.com
Requires-Python: >=3.10,<4.0
Classifier: Programming Language :: Python :: 3
Classifier: Programming Language :: Python :: 3.10
Classifier: Programming Language :: Python :: 3.11
Requires-Dist: docopt-ng (>=0.8.1,<0.9.0)
Requires-Dist: pendulum (>=2.1.2,<3.0.0)
Requires-Dist: piccolo[all] (>=0.96.0,<0.97.0)
Requires-Dist: platformdirs (>=2.5.3,<3.0.0)
Requires-Dist: pydantic (>=1.10.2,<2.0.0)
